{"month":"June","year":2019,"calendar":[{"id":"","title":"","shadate":"","geodate":"","status":"other_month","value":"","holiday":""},{"id":"","title":"","shadate":"","geodate":"","status":"other_month","value":"","holiday":""},{"id":"","title":"","shadate":"","geodate":"","status":"other_month","value":"","holiday":""},{"id":"","title":"","shadate":"","geodate":"","status":"other_month","value":"","holiday":""},{"id":"","title":"","shadate":"","geodate":"","status":"other_month","value":"","holiday":""},{"id":"","title":"","shadate":"","geodate":"","status":"other_month","value":"","holiday":""},{"id":"73","title":"sat","shadate":"1398\/3\/11","geodate":"2019-06-01","status":"default","value":1,"holiday":""},{"id":"74","title":"sun","shadate":"1398\/3\/12","geodate":"2019-06-02","status":"default","value":2,"holiday":""},{"id":"75","title":"mon","shadate":"1398\/3\/13","geodate":"2019-06-03","status":"default","value":3,"holiday":""},{"id":"76","title":"tue","shadate":"1398\/3\/14","geodate":"2019-06-04","status":"default","value":4,"holiday":""},{"id":"77","title":"wed","shadate":"1398\/3\/15","geodate":"2019-06-05","status":"default","value":5,"holiday":""},{"id":"78","title":"thu","shadate":"1398\/3\/16","geodate":"2019-06-06","status":"default","value":6,"holiday":""},{"id":"79","title":"fri","shadate":"1398\/3\/17","geodate":"2019-06-07","status":"default","value":7,"holiday":""},{"id":"80","title":"sat","shadate":"1398\/3\/18","geodate":"2019-06-08","status":"default","value":8,"holiday":""},{"id":"81","title":"sun","shadate":"1398\/3\/19","geodate":"2019-06-09","status":"default","value":9,"holiday":""},{"id":"82","title":"mon","shadate":"1398\/3\/20","geodate":"2019-06-10","status":"default","value":10,"holiday":""},{"id":"83","title":"tue","shadate":"1398\/3\/21","geodate":"2019-06-11","status":"default","value":11,"holiday":""},{"id":"84","title":"wed","shadate":"1398\/3\/22","geodate":"2019-06-12","status":"default","value":12,"holiday":""},{"id":"85","title":"thu","shadate":"1398\/3\/23","geodate":"2019-06-13","status":"default","value":13,"holiday":""},{"id":"86","title":"fri","shadate":"1398\/3\/24","geodate":"2019-06-14","status":"default","value":14,"holiday":""},{"id":"87","title":"sat","shadate":"1398\/3\/25","geodate":"2019-06-15","status":"default","value":15,"holiday":""},{"id":"88","title":"sun","shadate":"1398\/3\/26","geodate":"2019-06-16","status":"default","value":16,"holiday":""},{"id":"89","title":"mon","shadate":"1398\/3\/27","geodate":"2019-06-17","status":"default","value":17,"holiday":""},{"id":"90","title":"tue","shadate":"1398\/3\/28","geodate":"2019-06-18","status":"default","value":18,"holiday":""},{"id":"91","title":"wed","shadate":"1398\/3\/29","geodate":"2019-06-19","status":"default","value":19,"holiday":""},{"id":"92","title":"thu","shadate":"1398\/3\/30","geodate":"2019-06-20","status":"default","value":20,"holiday":""},{"id":"93","title":"fri","shadate":"1398\/3\/31","geodate":"2019-06-21","status":"default","value":21,"holiday":""},{"id":"94","title":"sat","shadate":"1398\/4\/1","geodate":"2019-06-22","status":"default","value":22,"holiday":""},{"id":"95","title":"sun","shadate":"1398\/4\/2","geodate":"2019-06-23","status":"default","value":23,"holiday":""},{"id":"96","title":"mon","shadate":"1398\/4\/3","geodate":"2019-06-24","status":"default","value":24,"holiday":""},{"id":"97","title":"tue","shadate":"1398\/4\/4","geodate":"2019-06-25","status":"default","value":25,"holiday":""},{"id":"98","title":"wed","shadate":"1398\/4\/5","geodate":"2019-06-26","status":"default","value":26,"holiday":""},{"id":"99","title":"thu","shadate":"1398\/4\/6","geodate":"2019-06-27","status":"default","value":27,"holiday":""},{"id":"100","title":"fri","shadate":"1398\/4\/7","geodate":"2019-06-28","status":"default","value":28,"holiday":""},{"id":"101","title":"sat","shadate":"1398\/4\/8","geodate":"2019-06-29","status":"default","value":29,"holiday":""},{"id":"102","title":"sun","shadate":"1398\/4\/9","geodate":"2019-06-30","status":"default","value":30,"holiday":""},{"id":"","title":"","shadate":"","geodate":"","status":"other_month","value":"","holiday":""},{"id":"","title":"","shadate":"","geodate":"","status":"other_month","value":"","holiday":""},{"id":"","title":"","shadate":"","geodate":"","status":"other_month","value":"","holiday":""},{"id":"","title":"","shadate":"","geodate":"","status":"other_month","value":"","holiday":""},{"id":"","title":"","shadate":"","geodate":"","status":"other_month","value":"","holiday":""},{"id":"","title":"","shadate":"","geodate":"","status":"other_month","value":"","holiday":""}]}